tlkcore/TLKCoreService.cpython-312-darwin.so
tlkcore/TMYBeamConfig.py
tlkcore/TMYCommService.cpython-312-darwin.so
tlkcore/TMYDFU.cpython-312-darwin.so
tlkcore/TMYLogging.py
tlkcore/TMYPublic.py
tlkcore/TMYUtils.cpython-312-darwin.so
tlkcore/__init__.py
tlkcore/db/TMYDBQueryer.cpython-312-darwin.so
tlkcore/db/__init__.py
tlkcore/tmydev/DevBBoard.cpython-312-darwin.so
tlkcore/tmydev/DevBBox.cpython-312-darwin.so
tlkcore/tmydev/DevBBoxDuo.cpython-312-darwin.so
tlkcore/tmydev/DevBBoxLite.cpython-312-darwin.so
tlkcore/tmydev/DevBBoxOne.cpython-312-darwin.so
tlkcore/tmydev/DevCloverCell.cpython-312-darwin.so
tlkcore/tmydev/DevPD.cpython-312-darwin.so
tlkcore/tmydev/DevRIS.cpython-312-darwin.so
tlkcore/tmydev/DevUDB.cpython-312-darwin.so
tlkcore/tmydev/DevUDBox.cpython-312-darwin.so
tlkcore/tmydev/DevUDC.cpython-312-darwin.so
tlkcore/tmydev/DevUDM.cpython-312-darwin.so
tlkcore/tmydev/RIS_pattern_generator.cpython-312-darwin.so
tlkcore/tmydev/TMYTableManager.cpython-312-darwin.so
tlkcore/tmydev/__init__.py
tlkcore/tmydev/device.cpython-312-darwin.so
tlkcore-2.4.4.dist-info/licenses/LICENSE.txt
tlkcore-2.4.4.dist-info/METADATA
tlkcore-2.4.4.dist-info/WHEEL
tlkcore-2.4.4.dist-info/top_level.txt
tlkcore-2.4.4.dist-info/RECORD
