Metadata-Version: 2.4
Name: tlkcore
Version: 2.4.4
Summary: TmxLab Kit Core engine (TLKCore) Hardware Driver Python API
Home-page: https://www.tmytek.com/
Author: TMYTEK Software Team
Author-email: rd2_common@tmytek.com
Project-URL: Documentation, https://tmytek-tlkcore.readthedocs-hosted.com/en/v2.4.4
Project-URL: Examples, https://github.com/TMYtek/tlkcore-examples/
Classifier: License :: Other/Proprietary License
Classifier: Development Status :: 4 - Beta
Classifier: Environment :: Console
Classifier: Intended Audience :: Developers
Classifier: Intended Audience :: Education
Classifier: Topic :: Software Development :: Libraries
Classifier: Topic :: Software Development :: Libraries :: Application Frameworks
Classifier: Topic :: Software Development :: Libraries :: Python Modules
Classifier: Topic :: Software Development :: Testing
Classifier: Topic :: System :: Hardware :: Hardware Drivers
Classifier: Programming Language :: Python
Classifier: Programming Language :: Python :: 3 :: Only
Classifier: Programming Language :: Python :: 3.8
Classifier: Programming Language :: Python :: 3.9
Classifier: Programming Language :: Python :: 3.10
Classifier: Programming Language :: Python :: 3.11
Classifier: Programming Language :: Python :: 3.12
Classifier: Programming Language :: Python :: Implementation :: CPython
Requires-Python: >=3.8
License-File: LICENSE.txt
Requires-Dist: psutil>=6.1.0
Requires-Dist: pyserial>=3.5
Requires-Dist: ft4222>=1.10.0
Requires-Dist: tftpy==0.8.5
Dynamic: author
Dynamic: author-email
Dynamic: classifier
Dynamic: description
Dynamic: description-content-type
Dynamic: home-page
Dynamic: license-file
Dynamic: project-url
Dynamic: requires-dist
Dynamic: requires-python
Dynamic: summary
